[{"name": "\u5289\u5b9b\u80b2", "email": "wanyuliu@ntut.edu.tw", "latestUpdate": "2012-02-01 15:29:35", "objective": "\u8868\u73fe\u6cd5\u5de5\u5177\u8207\u61c9\u7528\u3002\r\n\r\nThe course will introduce basic skills and applications of digital tools utilized for architectural presentation.", "schedule": "week01 2/20: Introduction\r\nweek02 2/27: (\u6821\u6176\u88dc\u5047)\r\nweek03 3/05: Photoshop I\r\nweek04 3/12: Photoshop II\r\nweek05 3/19: Photoshop III\r\nweek06 3/26: SketchUp I\r\nweek07 4/02: SketchUp II\r\nweek08 4/09: SketchUp III\r\nweek09 4/16: \u671f\u4e2d\u8003\u9031\r\nweek10 4/23: Mid-term review\r\nweek11 4/30: Diagram I\r\nweek12 5/07: Diagram II\r\nweek13 5/14: InDesign I\r\nweek14 5/21: InDesign II\r\nweek15 5/28: Layout I\r\nweek16 6/04: Layout II\r\nweek17 6/11: Final review\r\nweek18 6/18: \u671f\u672b\u8003\u9031", "scorePolicy": "Attendance: 25%\r\nExercise I: 15%\r\nMid-term review: 20%\r\nExercise II: 20%\r\nFinal review: 20%", "materials": "\u3000", "foreignLanguageTextbooks": false}]