[{"name": "\u9673\u82f1\u4e00", "email": "ichen@ntut.edu.tw", "latestUpdate": "2008-01-11 09:03:47", "objective": "\u900f\u904e\u539f\u7406\u89e3\u8aaa\u8207\u7cfb\u7d71\u5be6\u4f5c\uff0c\u4f7f\u5b78\u751f\u719f\u6089J2EE (Java 2 Enterprise Edition)\u67b6\u69cb\u4e0b\uff0c\u958b\u767c\u4f01\u696d\u7d1a\u7db2\u969b\u7db2\u8def\u61c9\u7528\u7cfb\u7d71\u6240\u9700\u4e4b\u5404\u9805\u6574\u5408\u6280\u8853\uff0c\u5305\u62ec\uff1a1. J2EE\u5e73\u53f0\u67b6\u69cb 2. J2EE\u7cfb\u7d71\u958b\u767c\u74b0\u5883 3. Java\u7269\u4ef6\u6280\u8853 4. JavaBeans\u5143\u4ef6\u8a2d\u8a08 5. JDBC\u8cc7\u6599\u5eab\u61c9\u7528 6. JSP\u7db2\u9801\u6280\u8853 7. Servlet\u5143\u4ef6\u6280\u8853 8. MVC\u67b6\u69cb\u8a2d\u8a08 9. JMS\u8a0a\u606f\u670d\u52d9 10. EJB\u5143\u4ef6\u8a2d\u8a08 11. Web Services\u6574\u5408\u6280\u8853 12. JAAS\u5b89\u5168\u6280\u8853 13. J2ME\u884c\u52d5\u901a\u4fe1\u6280\u8853", "schedule": "9/19 Java overview and current and future java career perspectives.\r\n9/26 Basic Java language programming\r\n10/5 Java OOP.\r\n10/10 Holiday, National Day.\r\n10/17 String object manipulation, Java application Demo.\r\n10/24 OOP, Encapsulation, Inheritance, Polymorphism, Interface\r\n10/31 Demo of OOP:Encapsulation, Inheritance, Polymorphism, Interface\r\n11/07 Demo of OOP:Encapsulation, Inheritance, Polymorphism, Interface\r\n11/14 Students' project demo\r\n11/21 J2EE Introduction\r\n11/28 JSP and Servlet\r\n12/05 Struts\r\n12/12 JDBC\r\n12/19 JSF & SDO\r\n12/26 Web Services\r\n2007 01/02 \u671f\u672b\u5c08\u6848\u8aaa\u660e\r\n2007 01/09 SDO & \u671f\u672b\u5c08\u6848\u5831\u544a", "scorePolicy": "\u3000", "materials": "\u66f8\u540d\uff1aJava 2\u6559\u5b78\u624b\u518a -- JDK 5\u7248 \u51fa\u7248\u793e\uff1a\u7881\u5cf0\r\n\u66f8\u540d\uff1aJ2EE \u6838\u5fc3\u5143\u7d20\u67b6\u69cb\u8207\u7a0b\u5f0f\u8a2d\u8a08 \u51fa\u7248\u793e\uff1a\uf90a\u79be\u8cc7\u8a0a\r\n\u66f8\u540d\uff1a Rational Application Developer V7 Programming Guide (Last updated on 21 September 2007)\r\n\u51fa\u7248\u793e\uff1aIBM RedBoo", "foreignLanguageTextbooks": false}]