[{"name": "\u66fe\u4e16\u6770", "email": "sjtzeng@ntut.edu.tw", "latestUpdate": "2007-09-20 10:02:15", "objective": "\u672c\u8ab2\u7a0b\u70ba\u5149\u96fb\u79d1\u6280\u7cfb\u57fa\u672c\u8ab2\u7a0b\u4e4b\u4e00\u3002\u5728\u5177\u6709\u7d71\u8a08\u53ca\u91cf\u5b50\u7684\u57fa\u672c\u89c0\u5ff5\u5f8c\uff0c\u53ef\u9078\u4fee\u672c\u8ab2\u7a0b\u3002\u5728\u56fa\u614b\u7269\u7406(I)\u7684\u8ab2\u7a0b\u4e2d\uff0c\u7531\u57fa\u790e\u53e4\u5178\u7269\u7406\u53ca\u91cf\u5b50\u7684\u89c0\u9ede\uff0c\u4ecb\u7d39\u91d1\u5c6c\u7684\u81ea\u7531\u96fb\u5b50\u7406\u8ad6\u3002\u4e14\u5c0d\u7d55\u7de3\u9ad4\u3001\u534a\u5c0e\u9ad4\u53ca\u91d1\u5c6c\u4e2d\u50b3\u5c0e\u7684\u534a\u53e4\u5178\u7406\u8ad6\u6a21\u578b\u7b49\uff0c\u5728\u672c\u8ab2\u7a0b\u4e2d\u6703\u9678\u7e8c\u4ecb\u7d39\u3002", "schedule": "1.Fermi Surface and Metal 2.Fermi Surface and Metal 3.Superconductivity 4.Superconductivity 5.Diamagnetism and Paramagnetism 6.Diamagnetism and Paramagnetism 7.Ferromagnetism and Antiferromagnetism 8.Ferromagnetism and Antiferromagnetism 9.Magnetic Resonance 10.Magnetic Resonance 11.Plasmons,Polaritons, and Polarons 12.Plasmons,Polaritons, and Polarons 13.Optical Processes and Excitons 14.Optical Processes and Excitons 15.Dielectrics and Ferroelectrics 16.Dielectrics and Ferroelectrics", "scorePolicy": "\u5e73\u5e38\u6210\u7e3e20%, \u671f\u4e2d\u800340%, \u671f\u672b\u800340%", "materials": "Solid state Physics (J.R. Hook)", "foreignLanguageTextbooks": false}]