[{"name": "\u9ec3\u5982\u7469", "email": "vinia@ntut.edu.tw", "latestUpdate": "2015-06-01 21:21:29", "objective": "\u7576\u4ee3\u82f1\u7f8e\u6d41\u884c\u5c0f\u8aaa,\u4f8b\u5982:\u9951\u9913\u904a\u6232,\u9f8d\u7d0b\u8eab\u7684\u5c11\u5973,\u6ce2\u897f\u5091\u514b\u68ee\u7cfb\u5217,\u66ae\u5149\u4e4b\u57ce\u7cfb\u5217,\u738b\u8005\u4e4b\u8072,\u5e36\u73cd\u73e0\u8033\u74b0\u7684\u5c11\u5973,\u6642\u7a7a\u65c5\u4eba\u4e4b\u59bb,\u59ca\u59ca\u7684\u5b88\u8b77\u8005\u7b49\u7b49,\u4e3b\u984c\u63a8\u9673\u51fa\u65b0,\u5167\u5bb9\u6263\u4eba\u5fc3\u5f26,\u6709\u7684\u53cd\u61c9\u7576\u524d\u7684\u6587\u5316\u8b70\u984c,\u6709\u7684\u8868\u73fe\u51fa\u5275\u65b0\u7684\u6587\u5b78\u60f3\u50cf,\u5728\u5728\u90fd\u6fc0\u767c\u8457\u540c\u5b78\u5011\u95b1\u8b80\u539f\u6587\u5c0f\u8aaa\u7684\u8208\u8da3.\u53c8\u7531\u65bc\u5c0f\u8aaa\u7684\u66f8\u5beb\u8a9e\u8a00\u70ba\u7576\u4eca\u82f1\u8a9e\u4e16\u754c\u6240\u4f7f\u7528,\u6c92\u6709\u5e74\u4ee3\u9694\u95a1,\u6240\u4ee5\u539f\u6587\u6d41\u884c\u5c0f\u8aaa\u4e5f\u662f\u512a\u826f\u7684\u82f1\u8a9e\u5b78\u7fd2\u6750\u6599.\u5728\u5b57\u5f59,\u7247\u8a9e,\u53e5\u578b,\u6bb5\u843d\u53ca\u6587\u7ae0\u7d50\u69cb,\u5230\u6545\u4e8b\u60c5\u7bc0\u767c\u5c55\u8207\u6df1\u5165\u63a2\u8a0e\u4e3b\u984c\u7684\u6bcf\u500b\u5c64\u9762\u4e0a,\u90fd\u63d0\u4f9b\u4e86\u8c50\u5bcc\u7684\u7d20\u6750,\u4f9b\u540c\u5b78\u5011\u5b78\u7fd2\u89c0\u6469.\u56e0\u6b64,\u672c\u8ab2\u7a0b\u5c07\u6311\u9078\u6ce2\u897f\u5091\u514b\u68ee\u8207\u5967\u6797\u5339\u4e9e\u795e\u7cfb\u5217\u5c0f\u8aaa\u4e94\u672c,\u898f\u5283\u9032\u5ea6,\u5728\u8ab2\u5802\u4e0a\u9032\u884c\u5c0e\u8b80\u8207\u8a0e\u8ad6,\u52a0\u5f37\u5b57\u5f59,\u53e5\u578b,\u8a13\u7df4\u8207\u6587\u7ae0\u7d50\u69cb\u4e0a\u7684\u5206\u6790,\u4e26\u589e\u9032\u53e3\u8a9e\u6717\u8aa6\u8207\u807d\u8b1b\u80fd\u529b,\u5e6b\u52a9\u540c\u5b78\u5011\u5728\u82f1\u8a9e\u66f8\u5beb,\u95b1\u8b80\u6280\u5de7,\u53e3\u8a9e\u8868\u9054,\u8de8\u6587\u5316\u4e86\u89e3\u8207\u601d\u8fa8\u80fd\u529b\u4e0a,\u7372\u5f97\u6700\u5927\u7684\u9032\u6b65!", "schedule": "Required textbooks: Percy Jackson the the Olympians series (5 books), available at the campus bookstore (\u672c\u6821\u7b2c\u516d\u6559\u5b78\u5927\u6a13\u5f8c\u68df\u4e00\u6a13\u5716\u6587\u90e8\u6709\u552e)\r\nSyllabus \u8ab2\u7a0b\u8868:\r\nWeek 1: Introduction\r\nWeek 2: The Lightning Thief\r\nWeek 3: The Lightning Thief\r\nWeek 4: The Lightning Thief\r\nWeek 5: The Lightning Thief\r\nWeek 6: The Sea of Monsters\r\nWeek 7: The Sea of Monsters\r\nWeek 8: The Sea of Monsters\r\nWeek 9): Mid-term exam week; The Sea of Monsters\r\nWeek 10: The Titan's Curse\t\r\nWeek 11: The Titan's Curse\r\nWeek 12: The Titan's Curse\r\nWeek 13: The Battle of the Labyrinth\r\nWeek 14: The Battle of the Labyrinth\r\nWeek 15: The Battle of the Labyrinth\r\nWeek 16: The Last Olympians\r\nWeek 17: The Last Olympians\r\nWeek 18: Final examination week; the Last Olympian", "scorePolicy": "Percentile distribution of final grades\u8a55\u5206\u767e\u5206\u6bd4:\r\n1. Vocabulary assignments: 5% X 3 = 15%\r\n2. Weekly tests and participation in classroom discussions:  25%\r\n3. Short essays (indivisual task): 10% X 3 = 30%\r\n4. Group oral presentation: 10% X 3 = 30%", "materials": "Reference\u53c3\u8003\u66f8\u7c4d:\r\n\u4e00\u751f\u5fc5\u8b80\u7684\u82f1\u6587\u5c0f\u8aaa:\u7d93\u5178\u8207\u5927\u773e\u5c0f\u8aaa\u5c0e\u8b80\u8cde\u6790. \u9673\u8d85\u660e \u8457. \u53f0\u5317: \u806f\u7d93 \u51fa\u7248, 2011\u5e74.\r\n\u4e00\u672c\u8b80\u901a\u4e16\u754c\u6587\u5b78\u540d\u8457. \u738b\u6dd1\u7d79 \u8b6f.\u53f0\u5317: \u5546\u5468\u51fa\u7248\u793e, 2010\u5e74.\r\n\u5c0f\u8aaa\u7684\u4e94\u5341\u5802\u8ab2. \u5927\u885b.\u6d1b\u5409 \u8457.  \u674e\u7dad\u62c9 \u8b6f. \u53f0\u5317: \u6728\u99ac, 2006\u5e74", "foreignLanguageTextbooks": false}]