[{"name": "\u694a\u5143\u68ee", "email": "ysyang@ntut.edu.tw", "latestUpdate": "2019-09-23 15:01:49", "objective": "\u672c\u8ab2\u7a0b\u5c07\u505a\u70ba\u5927\u4e00\u5b78\u751f\u5165\u5b78\u5f8c\u7b2c\u4e00\u9580\u7a0b\u5f0f\u8a9e\u8a00\u5960\u57fa\u8ab2\u7a0b\uff0c\u4f5c\u70ba\u7a0b\u5f0f\u8a2d\u8a08\u7684\u57fa\u790e\u3002\u6559\u6388\u5167\u5bb9\u5305\u62ec\u96fb\u8166\u904b\u4f5c\u6982\u5ff5\u3001\u7a0b\u5f0f\u8a2d\u8a08\u539f\u5247\u3001\u5206\u652f\u6558\u8ff0\u3001\u8ff4\u5708\u6558\u8ff0\u3001\u8f38\u51fa\u3001\u8f38\u5165\u6558\u8ff0\u3001\u9663\u5217\u8655\u7406\u3001\u5b57\u5143\u8655\u7406\u3001\u53ca\u5b50\u7a0b\u5f0f\u7b49\u8ab2\u984c\u3002", "schedule": "Week 1: Introduction to Computers and Programming. Assignment: Code::Blocks installation and testing\r\nWeek 2: Typing / Spreadsheet  formula, matrix multiplication and inversion \r\n    IF, MATCH, INDEX, angular unit conversion, angular rounding\r\nWeek 3: Spreadsheet formula: min, round, sqrt, if, countif, match, index and VBA basics\r\n    Exercises of Excel functions (Adjustment of angles)\r\n    VBA Basics (Developer option, macro, Range, variables) \r\nWeek 4: Variables and mathematical formula\r\nWeek 5: Branching Statements (Take-home Assignment)\r\nWeek 6: Loop \r\nWeek 7: Array / Vector / Matrix\r\nWeek 8: Midterm simulation\r\nWeek 9: Midterm\r\nWeek 10: Programming on mathematical formula (I)\r\nWeek 11: Programming on mathematical formula (II)\r\nWeek 12: Programming on Branching and Loop (I)\r\nWeek 13: Programming on Branching and Loop (II)\r\nWeek 14: Programming on Branching and Loop (III)\r\nWeek 15: Programming on Functions and Subroutines (I)\r\nWeek 16: Overall Review\r\nWeek 17: Final exam. simulation\r\nWeek 18: Final exam.", "scorePolicy": "Assignments and Activities: 25% +/- 5%\r\nMidterm: 25% +/- 5%\r\nFinal exam: 50% +/- 10%", "materials": "Lecture note.", "foreignLanguageTextbooks": true}]