[{"name": "\u845b\u5982\u921e", "email": "dablog@gmail.com", "latestUpdate": "2019-06-05 15:32:53", "objective": "\u8ab2\u7a0b\u898f\u5283\u7684\u76ee\u6a19\u70ba\u4ee5\u4e92\u52d5\u8a2d\u8a08\u7684\u7406\u8ad6\u70ba\u57fa\u790e\uff0c\u5be6\u52d9\u5c0e\u5411\u70ba\u539f\u5247\uff0c\u4f7f\u5b78\u7fd2\u8005\u80fd\u5c07\u5b78\u8853\u754c\u7684\u7406\u8ad6\u8207\u7522\u696d\u754c\u7684\u5be6\u52d9\u52a0\u4ee5\u7d50\u5408\u4ee5\u5145\u5be6\u5c0d\u65bc\u4e92\u52d5\u8a2d\u8a08\u5177\u6709\u7684\u4e86\u89e3\u3002\u5b78\u7fd2\u7684\u5167\u5bb9\u5305\u542b\u4e92\u52d5\u8a2d\u8a08\u7cfb\u7d71\u69cb\u6210\u8981\u7d20\u3001\u5be6\u52d9\u8207\u7406\u8ad6\u57fa\u790e\u3001\u65b9\u6cd5\u8207\u6280\u8853\u3001\u79d1\u6280\u652f\u63f4\u8207\u61c9\u7528\u7b49\u55ae\u5143\uff0c\u5404\u55ae\u5143\u4e26\u5305\u542b\u4e0d\u540c\u4e92\u52d5\u8a2d\u8a08\u500b\u6848\u7684\u7814\u8a0e\uff0c\u4f7f\u7406\u8ad6\u80fd\u8207\u5be6\u52d9\u9032\u884c\u9a57\u8b49\u3002\u8ab2\u7a0b\u4ea6\u5b89\u6392\u81f3\u76f8\u95dc\u9818\u57df\u696d\u754c\u7684\u53c3\u8a2a\u4ee5\u53ca\u4e92\u52d5\u76f8\u95dc\u5c55\u89bd\u53c3\u89c0\uff0c\u4ee5\u52a0\u6df1\u5c0d\u65bc\u4e92\u52d5\u8a2d\u8a08\u5be6\u52d9\u7684\u5370\u8c61\u8207\u4e86\u89e3\u3002\r\nThe course aims to develop broad understanding on interaction design for students, based on theory and practice course structure. Course topics include essential factors of interactive system, interaction design theory and practice, methods and techniques, technical support and application. Course also incorporates case studies, company visits and exhibitions relevant to interaction design to enhance the understanding of integrating theory and practice.", "schedule": "\u4ee5\u8ab2\u5802\u516c\u5e03\u70ba\u6e96\u3002", "scorePolicy": "\u51fa\u5e2d\u8207\u7c21\u5831", "materials": "\u4e92\u52d5\u8a2d\u8a08\u6982\u8ad6\r\nby \u674e\u4f86\u6625\u3001\u9673\u5733\u537f\u3001\u66f9\u7b71\u73a5", "foreignLanguageTextbooks": false}]