[{"name": "\u674e\u6625\u7a4e", "email": "leech@ntut.edu.tw", "latestUpdate": "2020-06-08 16:18:51", "objective": "\u5148\u4fee\u8ab2\u7a0b\uff1a3001011\u6216\u8ca0\u8cac\u6559\u6388\u540c\u610f\u3002\u529b\u3001\u8cea\u91cf\u8207\u52a0\u901f\u5ea6\u3001\u8cea\u9ede\u904b\u52d5\u5b78\u3001\u8cea\u9ede\u52d5\u529b\u5b78\u3001\u529f\u8207\u80fd\u3001\u885d\u91cf\u8207\u52d5\u91cf\u3001\u525b\u9ad4\u904b\u52d5\u3001\u525b\u9ad4\u7cfb\u7684\u52d5\u529b\u5b78\u3002", "schedule": "1-2\u9031\uff1aKinematics of a particle\r\n3-4\u9031\uff1aKinetics of a particle: Force and acceleration\r\n5-6\u9031\uff1aKinetics of a particle: Work and energy\r\n7\u9031\uff1aMid-term #1\r\n8-9\u9031\uff1aKinetics of a particle: Impulse and momentum\r\n10-11\u9031\uff1aPlanar kinematics of a rigid body\r\n12-13\u9031\uff1aPlanar kinetics of a rigid body: Force and acceleration\r\n14\u9031\uff1aMid-term #2\r\n15-16\u9031\uff1aPlanar kinetics of a rigid body: Work and energy\r\n17-18\u9031\uff1aPlanar kinetics of a rigid body: Impulse and momentum\r\nFinal Exam", "scorePolicy": "\u51fa\u5e2d\u53ca\u5e73\u6642\u8868\u73fe\uff1a10\uff05\r\n\u671f\u4e2d\u8003\uff031\uff1a30\uff05\r\n\u671f\u4e2d\u8003\uff032\uff1a30\uff05\r\n\u671f\u672b\u8003\uff1a30\uff05", "materials": "1. Vector Mechanics for Engineers- Dynamics, by Beer, Johnston, et al., 11th edition, McGraw-Hill Pub. Co., 2016\r\n2. Engineering Mechanicas- Dynamics, by Hibbeler, 14/e, 2017, Pearson", "foreignLanguageTextbooks": true}]