[{"name": "\u5f6d\u670b\u7fa4", "email": "pcpeng@ntut.edu.tw", "latestUpdate": "2020-06-01 23:35:51", "objective": "1.\u6df1\u5ea6\u5b78\u7fd2\u4ecb\u7d39\uff0c2.\u76e3\u7763\u5f0f\u5b78\u7fd2\uff0c3.\u7121\u76e3\u7763\u5f0f\u5b78\u7fd2\uff0c4.\u7269\u806f\u7db2\uff0c5.\u611f\u77e5\u5c64\uff0c6.\u7db2\u8def\u5c64\uff0c7.\u61c9\u7528\u5c64\uff0c8. \u6df1\u5ea6\u5b78\u7fd2\u8207\u7269\u806f\u7db2\u61c9\u7528\u5be6\u4f8b\u3002\r\n1. Introduction to Deep Learning, 2. Supervised Learning, 3. Unsupervised Learning, 4. Internet of Things, 5. Perception Layer, 6. Network Layer, 7. Application Layer, 8. Deep Learning and Internet of Things", "schedule": "1-2. Introduction to Deep Learning, \r\n3-4. Supervised Learning, \r\n5-6. Unsupervised Learning, \r\n7-8. Internet of Things, \r\n9-10. Perception Layer, \r\n11-12. Network Layer, \r\n13-14. Application Layer, \r\n15-18. Deep Learning and Internet of Things", "scorePolicy": "Homework: 60%\r\nFinal report: 40%", "materials": "\u6df1\u5ea6\u5b78\u7fd2\u8207\u7269\u806f\u7db2\u61c9\u7528", "foreignLanguageTextbooks": true}]