[{"name": "\u6797\u4fe1\u6a19", "email": "hplin@en.ntut.edu.tw", "latestUpdate": "2017-01-19 13:21:36", "objective": "1.\u4fe1\u865f\u8207\u7dda\u6027\u7cfb\u7d71\r\n2.\u96a8\u6a5f\u7a0b\u5e8f\r\n3.\u985e\u6bd4\u8abf\u8b8a\r\n4.\u985e\u6b64\u8207\u6578\u4f4d\u8f49\u63db\r\n5.\u57fa\u983b\u6578\u4f4d\u50b3\u8f38\r\n6.\u6709\u9650\u983b\u5bec\u901a\u9053\u6578\u4f4d\u50b3\u8f38\r\n7.\u6578\u4f4d\u8f09\u6ce2\u50b3\u8f38\r\n8.\u901a\u9053\u5bb9\u91cf\u8207\u7de8\u78bc\r\n9.\u5c55\u983b\u901a\u8a0a\u7cfb\u7d71\r\n10.Simulink\u4ecb\u7d39\u8207\u5be6\u4f8b\u63a2\u8a0e", "schedule": "3 weeks \u6578\u4f4d\u901a\u8a0a\u6280\u8853\r\n7 weeks Labview\u7684\u64cd\u4f5c\u8207\u7a0b\u5f0f\u8a2d\u8a08\r\n3 weeks \u8abf\u8b8a\u8207\u7de8\u78bc\u6280\u8853\r\n2 weeks \u7121\u7dda\u901a\u9053\u7684\u7279\u6027\u8207\u514b\u670d\u65b9\u6cd5\r\n2 weeks \u7121\u7dda\u5340\u57df\u7db2\u8defIEEE 802.11a\u7cfb\u7d71\u4e4b\u50b3\u8f38\u6280\u8853\u8207\u6548\u80fd\u5206\u6790", "scorePolicy": "Lab: \u516d\u6b21\uff0c\u6bcf\u6b2112%\uff0c\u517172%\r\n\u671f\u672b\u8003\uff1a 25%\r\n\u51fa\u5e2d\u7387\uff1a3%", "materials": "Reference:\r\n1.  D.P. Agrawal, \u201cIntroduction to Wireless and Mobile Systems\u201d, 2003, Thomson Learning, Inc. \r\n2.  NI Labview Tutorial", "foreignLanguageTextbooks": false}]