[{"name": "\u9ec3\u7d39\u83ef", "email": "hsf@ntut.edu.tw", "latestUpdate": "2012-01-30 16:39:41", "objective": "2/19: C Introduction\r\n2/26: Loop: for/while\r\n3/5:  Output: print\r\n3/12: Variable, Array, Pointer\r\n3/19: I/O: Print/scanf, Sorting\r\n3/26: Text File Process\r\n4/2:  File Read/Write/Sorting/Edit/Delete\r\n4/9:  Subroutine, Local Variable\r\n4/16: \u671f\u4e2d\u8003\r\n4/23: Subroutine, Variable/2D-pointer\r\n4/30: TCP Sync. Mode\r\n5/7:  UDP Sync. Mode\r\n5/14: File Transfer vs.\r\n5/21: Broadcasting\r\n5/28: \u7aef\u5348\u7bc0\r\n6/4:  Chat-Room-I\r\n6/11: Chat-Room-II\r\n6/18: \u671f\u672b\u8003", "schedule": "2/19: C Introduction\r\n2/26: Loop: for/while\r\n3/5:  Output: print\r\n3/12: Variable, Array, Pointer\r\n3/19: I/O: Print/scanf, Sorting\r\n3/26: Text File Process\r\n4/2:  File Read/Write/Sorting/Edit/Delete\r\n4/9:  Subroutine, Local Variable\r\n4/16: \u671f\u4e2d\u8003\r\n4/23: Subroutine, Variable/2D-pointer\r\n4/30: TCP Sync. Mode\r\n5/7:  UDP Sync. Mode\r\n5/14: File Transfer vs.\r\n5/21: Broadcasting\r\n5/28: \u7aef\u5348\u7bc0\r\n6/4:  Chat-Room-I\r\n6/11: Chat-Room-II\r\n6/18: \u671f\u672b\u8003", "scorePolicy": "\u671f\u4e2d\u8003: 30%\r\n\u671f\u672b\u8003: 30%\r\n\u4f5c\u696d:   40%", "materials": "C\u7a0b\u5f0f\u8a2d\u8a08, \u65d7\u6a19,", "foreignLanguageTextbooks": false}]