[{"name": "\u90ed\u973d\u6176", "email": "kuocc@ntut.edu.tw", "latestUpdate": "2011-09-12 16:39:26", "objective": "\u672c\u8ab2\u7a0b\u5f9e\u7269\u7406\u7684\u89c0\u9ede\u8ac7\u8ff0\u5206\u5b50\u6750\u6599\u3002\u5167\u5bb9\u5305\u62ec\u5982\u4e0b\u4e3b\u984c\uff1a1.\t\u529b\u5b782.\t\u96fb\u5b783.\t\u5149\u5b784.\t\u78c1\u5b785.\t\u751f\u7269\u7269\u7406", "schedule": "\u9031\u6b21\t\u65e5\u671f\t\u9032\u5ea6\u5927\u7db1\t\n1\t09\u6708 12\u65e5\t\u4e2d\u79cb\u7bc0\n\t\n2\t09\u6708 19\u65e5\t\u8ab2\u7a0b\u5c0e\u8ad6\u3001\u8a55\u5206\u8aaa\u660e+ Ch1 Measurement(\u5ea6\u91cf)\n\t\n3\t09\u6708 26\u65e5\tCh 2 Motion Along A Straight Line (\u76f4\u7dda\u904b\u52d5)\n\t\n4\t10\u670803\u65e5\tCh 2 Motion Along A Straight Line (\u76f4\u7dda\u904b\u52d5)\n\t\n5\t10\u670810\u65e5\t\u96d9\u5341\u7bc0(\u653e\u5047)\n\t\n6\t10\u670817\u65e5\tCh 3 Vectors (\u5411\u91cf)\n\t\n7\t10\u670824\u65e5\tCh 3 Vectors (\u5411\u91cf)\n\t\n8\t10\u670831\u65e5\tTest-1\n\t\n9\t11\u670807\u65e5\tCh 4 Motion In Two And Three Dimensions (\u4e8c\u7dad\u8207\u4e09\u7dad\u904b\u52d5)\n\t\n10\t11\u670814\u65e5\tCh4 Motion In Two And Three Dimensions (\u4e8c\u7dad\u8207\u4e09\u7dad\u904b\u52d5)\n\t\n11\t11\u670821\u65e5\tCh5 Force And Motion-I (\u725b\u9813\u904b\u52d5\u5b9a\u5f8b)\n\t\n12\t11\u670828\u65e5\tCh5 Force And Motion-II (\u725b\u9813\u904b\u52d5\u5b9a\u5f8b)\n\t\n13\t12\u670805\u65e5\tTest-2\n\t\n14\t12\u670812\u65e5\tCh 6 Force And Motion-II (\u6469\u64e6\u529b\u3001\u66f3\u529b\u53ca\u5411\u5fc3\u529b)\n\t\n15\t12\u670819\u65e5\tCh 6 Force And Motion-II (\u6469\u64e6\u529b\u3001\u66f3\u529b\u53ca\u5411\u5fc3\u529b)\n\t\n16\t12\u670826\u65e5\tCh 7 Kinetic Energy And Work (\u529f-\u52d5\u80fd\u5b9a\u7406)\n\t\n17\t01\u670802\u65e5\tCh 7 Kinetic Energy And Work (\u529f-\u52d5\u80fd\u5b9a\u7406)\n\t\n18\t01\u670809\u65e5\tTest-3", "scorePolicy": "\u8a55\u5206\u6a19\u6e96\uff1a Test-1 (20%)  Test-2 (20%)  Test-3 (20%) \u51fa\u5e2d(10%) \u4f5c\u696d(30%)", "materials": "\u8ab2\u5802\u7528\u66f8\uff1a \n1.\t\u4e3b\u8981a : \u8ab2\u5802\u8b1b\u7fa9\n2.\t\u4e3b\u8981b:  Fundamentals of Physics (\u666e\u901a\u7269\u7406\u5b78)/ David Halliday/ Wiely (\u6b50\u4e9e\u66f8\u5c40\u4ee3\u7406)", "foreignLanguageTextbooks": false}]